Metadata-Version: 2.1
Name: texta-entity-linker
Version: 1.0.2
Summary: TEXTA Entity Linker
Home-page: https://git.texta.ee/texta/texta-entity-linker
Author: TEXTA
Author-email: info@texta.ee
License: GPLv3
Platform: UNKNOWN
